{"labels": ["2020-03-28", "2020-04-05", "2020-04-11"], "datasets": [{"data": ["null", "885.6", "885.5"], "label": "in ELN bootable base aarch64", "fill": "false"}, {"data": ["null", "887.2", "887.0"], "label": "in ELN bootable base armv7hl", "fill": "false"}, {"data": ["null", "1000.5", "1000.5"], "label": "in ELN bootable base ppc64le", "fill": "false"}, {"data": ["null", "778.8", "778.8"], "label": "in ELN bootable base s390x", "fill": "false"}, {"data": ["null", "844.7", "844.6"], "label": "in ELN bootable base x86_64", "fill": "false"}, {"data": ["308.2", "308.8", "308.8"], "label": "in Empty aarch64", "fill": "false"}, {"data": ["282.4", "283.1", "283.1"], "label": "in Empty armv7hl", "fill": "false"}, {"data": ["316.5", "317.0", "317.0"], "label": "in Empty ppc64le", "fill": "false"}, {"data": ["292.4", "293.0", "293.0"], "label": "in Empty s390x", "fill": "false"}, {"data": ["292.5", "293.2", "293.2"], "label": "in Empty x86_64", "fill": "false"}]}