{"labels": ["2020-03-28", "2020-04-05", "2020-04-08"], "datasets": [{"data": ["null", "1261.6", "1261.5"], "label": "in ELN bootable base aarch64", "fill": "false"}, {"data": ["null", "1219.6", "1219.3"], "label": "in ELN bootable base armv7hl", "fill": "false"}, {"data": ["null", "1399.2", "1399.1"], "label": "in ELN bootable base ppc64le", "fill": "false"}, {"data": ["null", "1145.0", "1145.0"], "label": "in ELN bootable base s390x", "fill": "false"}, {"data": ["null", "1226.3", "1226.1"], "label": "in ELN bootable base x86_64", "fill": "false"}, {"data": ["714.1", "714.7", "714.7"], "label": "in Empty aarch64", "fill": "false"}, {"data": ["641.9", "642.5", "642.5"], "label": "in Empty armv7hl", "fill": "false"}, {"data": ["749.4", "750.1", "750.2"], "label": "in Empty ppc64le", "fill": "false"}, {"data": ["688.9", "689.5", "689.5"], "label": "in Empty s390x", "fill": "false"}, {"data": ["703.5", "704.2", "704.2"], "label": "in Empty x86_64", "fill": "false"}]}