{"labels": ["2020-03-28", "2020-04-05", "2020-04-12", "2020-04-19", "2020-04-22", "2020-04-29"], "datasets": [{"data": ["400.6", "401.4", "401.4", "401.4", "401.4", "401.4"], "label": "aarch64", "fill": "false"}, {"data": ["347.4", "348.2", "348.2", "348.2", "348.2", "348.2"], "label": "armv7hl", "fill": "false"}, {"data": ["417.4", "418.2", "418.2", "418.2", "418.2", "418.3"], "label": "ppc64le", "fill": "false"}, {"data": ["365.8", "366.7", "366.7", "366.7", "366.7", "366.7"], "label": "s390x", "fill": "false"}, {"data": ["365.9", "366.8", "366.8", "366.8", "366.8", "366.8"], "label": "x86_64", "fill": "false"}]}