{"labels": ["2020-03-28", "2020-04-03"], "datasets": [{"data": ["null", "null"], "label": "in ELN Buildroot Workload aarch64", "fill": "false"}, {"data": ["null", "null"], "label": "in ELN Buildroot Workload armv7hl", "fill": "false"}, {"data": ["null", "null"], "label": "in ELN Buildroot Workload ppc64le", "fill": "false"}, {"data": ["null", "null"], "label": "in ELN Buildroot Workload s390x", "fill": "false"}, {"data": ["null", "null"], "label": "in ELN Buildroot Workload x86_64", "fill": "false"}]}