{"labels": ["2020-03-28", "2020-04-05", "2020-04-12", "2020-04-17"], "datasets": [{"data": ["431.9", "432.6", "432.6", "432.6"], "label": "aarch64", "fill": "false"}, {"data": ["374.8", "375.5", "375.5", "375.5"], "label": "armv7hl", "fill": "false"}, {"data": ["451.8", "452.4", "452.4", "452.4"], "label": "ppc64le", "fill": "false"}, {"data": ["401.3", "402.0", "402.0", "402.0"], "label": "s390x", "fill": "false"}, {"data": ["399.7", "400.5", "400.5", "400.5"], "label": "x86_64", "fill": "false"}]}