{"labels": ["2020-03-28", "2020-04-05", "2020-04-12", "2020-04-17"], "datasets": [{"data": ["419.4", "418.3", "418.3", "418.5"], "label": "aarch64", "fill": "false"}, {"data": ["374.0", "373.7", "373.7", "373.8"], "label": "armv7hl", "fill": "false"}, {"data": ["434.1", "431.0", "431.0", "431.1"], "label": "ppc64le", "fill": "false"}, {"data": ["388.3", "388.1", "388.1", "388.3"], "label": "s390x", "fill": "false"}, {"data": ["396.0", "395.5", "395.6", "395.7"], "label": "x86_64", "fill": "false"}]}