{"labels": ["2020-03-28", "2020-04-05", "2020-04-12", "2020-04-19", "2020-04-22", "2020-05-01"], "datasets": [{"data": ["213.1", "212.3", "212.4", "212.7", "212.7", "212.5"], "label": "Fedora 31 armv7hl", "fill": "false"}, {"data": ["352.5", "351.7", "351.7", "351.7", "351.7", "351.5"], "label": "Fedora 31 armv7hl", "fill": "false"}, {"data": ["184.6", "184.2", "184.2", "184.5", "184.5", "184.2"], "label": "Fedora 31 armv7hl", "fill": "false"}, {"data": ["167.3", "166.9", "166.9", "173.5", "173.5", "173.3"], "label": "Fedora 31 armv7hl", "fill": "false"}, {"data": ["129.9", "129.4", "129.5", "129.5", "129.5", "129.2"], "label": "Fedora 31 armv7hl", "fill": "false"}]}