{"labels": ["2020-03-28", "2020-04-05", "2020-04-12", "2020-04-19", "2020-04-22", "2020-05-02"], "datasets": [{"data": ["null", "1080.9", "1080.8", "1080.8", "1080.8", "1083.5"], "label": "aarch64", "fill": "false"}, {"data": ["null", "1068.5", "1068.3", "1068.3", "1068.3", "1070.9"], "label": "armv7hl", "fill": "false"}, {"data": ["null", "1200.4", "1200.5", "1200.5", "1200.5", "1203.2"], "label": "ppc64le", "fill": "false"}, {"data": ["null", "963.1", "963.2", "963.2", "963.2", "965.7"], "label": "s390x", "fill": "false"}, {"data": ["null", "1037.9", "1037.9", "1037.9", "1037.9", "1040.5"], "label": "x86_64", "fill": "false"}]}