{"labels": ["2020-03-28", "2020-04-05", "2020-04-12"], "datasets": [{"data": ["null", "1213.9", "1215.4"], "label": "in ELN bootable base aarch64", "fill": "false"}, {"data": ["null", "881.5", "881.3"], "label": "in ELN bootable base armv7hl", "fill": "false"}, {"data": ["null", "1379.7", "1381.5"], "label": "in ELN bootable base ppc64le", "fill": "false"}, {"data": ["null", "772.3", "772.4"], "label": "in ELN bootable base s390x", "fill": "false"}, {"data": ["null", "1192.5", "1194.1"], "label": "in ELN bootable base x86_64", "fill": "false"}, {"data": ["724.2", "724.9", "726.4"], "label": "in Empty aarch64", "fill": "false"}, {"data": ["0.0", "0.0", "0.0"], "label": "in Empty armv7hl", "fill": "false"}, {"data": ["794.2", "794.8", "796.6"], "label": "in Empty ppc64le", "fill": "false"}, {"data": ["0.0", "0.0", "0.0"], "label": "in Empty s390x", "fill": "false"}, {"data": ["713.2", "713.9", "715.6"], "label": "in Empty x86_64", "fill": "false"}]}