{"labels": ["2020-03-28", "2020-04-05", "2020-04-12", "2020-04-16"], "datasets": [{"data": ["503.8", "501.9", "502.0", "501.9"], "label": "aarch64", "fill": "false"}, {"data": ["440.9", "440.1", "440.2", "440.2"], "label": "armv7hl", "fill": "false"}, {"data": ["535.3", "531.6", "531.6", "531.6"], "label": "ppc64le", "fill": "false"}, {"data": ["425.6", "424.9", "424.9", "424.9"], "label": "s390x", "fill": "false"}, {"data": ["467.6", "466.5", "466.6", "466.5"], "label": "x86_64", "fill": "false"}]}