{"labels": ["2020-03-28", "2020-04-05", "2020-04-12", "2020-04-19", "2020-04-22", "2020-04-27"], "datasets": [{"data": ["814.9", "813.9", "813.9", "814.1", "814.1", "814.4"], "label": "aarch64", "fill": "false"}, {"data": ["683.7", "683.2", "683.3", "683.6", "683.6", "683.6"], "label": "armv7hl", "fill": "false"}, {"data": ["861.6", "860.7", "860.8", "861.1", "861.1", "861.3"], "label": "ppc64le", "fill": "false"}, {"data": ["728.9", "728.5", "728.6", "728.9", "728.9", "729.2"], "label": "s390x", "fill": "false"}, {"data": ["743.4", "742.9", "742.9", "743.3", "743.3", "743.5"], "label": "x86_64", "fill": "false"}]}